Workbook

Sheet Inputs
A1: Snack Stall: Projection Inputs
A2: Blue text = numbers you can change. Yellow = guesses to replace with your own. Every other tab updates from this one.
A4: Item | B4: Size | C4: Price ($) | D4: Ingredient cost per unit ($) | E4: Stock prepared (units) | F4: Low (units / day) | G4: Expected (units / day) | H4: High (units / day) | I4: Notes
A5: Medhu Vadai | B5: 1 plate | C5: 6 | D5: 0 | E5: 50 | F5: 10 | G5: 20 | H5: 35 | I5: Prices: from you (Idly $8 and Rose Milk $4, as updated in the tracker).
A6: Paneer Puff | B6: 1 piece | C6: 4 | D6: 0 | E6: 40 | F6: 10 | G6: 20 | H6: 35 | I6: Units per day: my starting guesses for a small weekend stall. Replace with your own.
A7: Podi Idly | B7: 1 plate | C7: 8 | D7: 0 | E7: 30 | F7: 8 | G7: 15 | H7: 25 | I7: Stock: from you (50 / 40 / 30 / 20 for the weekend).
A8: Rose Milk | B8: 10 oz | C8: 4 | D8: 0 | E8: 20 | F8: 12 | G8: 25 | H8: 40 | I8: Ingredient cost: 0 because your $50 cooking items are in fixed costs. Enter a per-unit cost to model buying more for bigger days.
I9: Rows 9-10: spare rows for new items.
A12: Fixed costs | B12: Amount ($)
A13: Stall fee | B13: 60 | C13: From you.
A14: Supplies | B14: 50 | C14: From you.
A15: Cooking items | B15: 50 | C15: From you.
A16: Other | B16: 0 | C16: Ice, cups, parking, etc.
A17: Total fixed costs | B17: =SUM(B13:B16) -> 160
A19: Event
A20: Days open | B20: 2 | C20: Saturday and Sunday.
A21: Hours open per day | B21: 6 | C21: Guess. Used only for items per hour.

Sheet Projection
A1: Weekend Sales Projection
A2: Units are per weekend (units per day x days open). Change the numbers on the Inputs tab.
A4: Item | B4: Price ($) | C4: Low units | D4: Low sales ($) | E4: Expected units | F4: Expected sales ($) | G4: High units | H4: High sales ($)
A5: =IF(Inputs!A5="","",Inputs!A5) -> Medhu Vadai | B5: =Inputs!C5 -> 6 | C5: =Inputs!F5*Inputs!$B$20 -> 20 | D5: =C5*$B5 -> 120 | E5: =Inputs!G5*Inputs!$B$20 -> 40 | F5: =E5*$B5 -> 240 | G5: =Inputs!H5*Inputs!$B$20 -> 70 | H5: =G5*$B5 -> 420
A6: =IF(Inputs!A6="","",Inputs!A6) -> Paneer Puff | B6: =Inputs!C6 -> 4 | C6: =Inputs!F6*Inputs!$B$20 -> 20 | D6: =C6*$B6 -> 80 | E6: =Inputs!G6*Inputs!$B$20 -> 40 | F6: =E6*$B6 -> 160 | G6: =Inputs!H6*Inputs!$B$20 -> 70 | H6: =G6*$B6 -> 280
A7: =IF(Inputs!A7="","",Inputs!A7) -> Podi Idly | B7: =Inputs!C7 -> 8 | C7: =Inputs!F7*Inputs!$B$20 -> 16 | D7: =C7*$B7 -> 128 | E7: =Inputs!G7*Inputs!$B$20 -> 30 | F7: =E7*$B7 -> 240 | G7: =Inputs!H7*Inputs!$B$20 -> 50 | H7: =G7*$B7 -> 400
A8: =IF(Inputs!A8="","",Inputs!A8) -> Rose Milk | B8: =Inputs!C8 -> 4 | C8: =Inputs!F8*Inputs!$B$20 -> 24 | D8: =C8*$B8 -> 96 | E8: =Inputs!G8*Inputs!$B$20 -> 50 | F8: =E8*$B8 -> 200 | G8: =Inputs!H8*Inputs!$B$20 -> 80 | H8: =G8*$B8 -> 320
A9: =IF(Inputs!A9="","",Inputs!A9) | B9: =Inputs!C9 -> 0 | C9: =Inputs!F9*Inputs!$B$20 -> 0 | D9: =C9*$B9 -> 0 | E9: =Inputs!G9*Inputs!$B$20 -> 0 | F9: =E9*$B9 -> 0 | G9: =Inputs!H9*Inputs!$B$20 -> 0 | H9: =G9*$B9 -> 0
A10: =IF(Inputs!A10="","",Inputs!A10) | B10: =Inputs!C10 -> 0 | C10: =Inputs!F10*Inputs!$B$20 -> 0 | D10: =C10*$B10 -> 0 | E10: =Inputs!G10*Inputs!$B$20 -> 0 | F10: =E10*$B10 -> 0 | G10: =Inputs!H10*Inputs!$B$20 -> 0 | H10: =G10*$B10 -> 0
A11: Total | C11: =SUM(C5:C10) -> 80 | D11: =SUM(D5:D10) -> 424 | E11: =SUM(E5:E10) -> 160 | F11: =SUM(F5:F10) -> 840 | G11: =SUM(G5:G10) -> 270 | H11: =SUM(H5:H10) -> 1420
A13: Summary | B13: Low | C13: Expected | D13: High
A14: Sales | B14: =D11 -> 424 | C14: =F11 -> 840 | D14: =H11 -> 1420
A15: Ingredient cost (per-unit) | B15: =SUMPRODUCT(C5:C10,Inputs!$D$5:$D$10) -> 0 | C15: =SUMPRODUCT(E5:E10,Inputs!$D$5:$D$10) -> 0 | D15: =SUMPRODUCT(G5:G10,Inputs!$D$5:$D$10) -> 0
A16: Fixed costs | B16: =Inputs!$B$17 -> 160 | C16: =Inputs!$B$17 -> 160 | D16: =Inputs!$B$17 -> 160
A17: Profit / loss | B17: =B14-B15-B16 -> 264 | C17: =C14-C15-C16 -> 680 | D17: =D14-D15-D16 -> 1260
A18: Profit margin | B18: =IF(B14=0,0,B17/B14) -> 0.62264151 | C18: =IF(C14=0,0,C17/C14) -> 0.80952381 | D18: =IF(D14=0,0,D17/D14) -> 0.88732394
A19: Items sold (weekend) | B19: =C11 -> 80 | C19: =E11 -> 160 | D19: =G11 -> 270
A20: Items per hour | B20: =IF(Inputs!$B$20*Inputs!$B$21=0,0,B19/(Inputs!$B$20*Inputs!$B$21)) -> 6.6666667 | C20: =IF(Inputs!$B$20*Inputs!$B$21=0,0,C19/(Inputs!$B$20*Inputs!$B$21)) -> 13.333333 | D20: =IF(Inputs!$B$20*Inputs!$B$21=0,0,D19/(Inputs!$B$20*Inputs!$B$21)) -> 22.5
A21: Average price per item | B21: =IF(B19=0,0,B14/B19) -> 5.3 | C21: =IF(C19=0,0,C14/C19) -> 5.25 | D21: =IF(D19=0,0,D14/D19) -> 5.2592593
A22: Profit per item before fixed costs | B22: =IF(B19=0,0,(B14-B15)/B19) -> 5.3 | C22: =IF(C19=0,0,(C14-C15)/C19) -> 5.25 | D22: =IF(D19=0,0,(D14-D15)/D19) -> 5.2592593
A23: Items to sell to break even | B23: =IF(B22<=0,0,ROUNDUP(Inputs!$B$17/B22,0)) -> 31 | C23: =IF(C22<=0,0,ROUNDUP(Inputs!$B$17/C22,0)) -> 31 | D23: =IF(D22<=0,0,ROUNDUP(Inputs!$B$17/D22,0)) -> 31
A24: Sales needed to break even ($) | B24: =B23*B21 -> 164.3 | C24: =C23*C21 -> 162.75 | D24: =D23*D21 -> 163.03704
A26: Break-even uses each scenario's mix of items. With mostly Paneer Puffs ($4) you need more items than with mostly Vadai or Idly ($6).

Sheet What-if
A1: What-if: Weekend Profit
A2: Weekend profit for each mix of items sold per day (down) and average price per item (across). Green = profit, red = loss. Change the blue numbers to test other cases.
A4: Items sold per day / Avg price | B4: 4 | C4: 4.5 | D4: 5 | E4: 5.5 | F4: 6
A5: 10 | B5: =$A5*$B$18*(B$4-$B$16)-$B$17 -> -80 | C5: =$A5*$B$18*(C$4-$B$16)-$B$17 -> -70 | D5: =$A5*$B$18*(D$4-$B$16)-$B$17 -> -60 | E5: =$A5*$B$18*(E$4-$B$16)-$B$17 -> -50 | F5: =$A5*$B$18*(F$4-$B$16)-$B$17 -> -40
A6: 20 | B6: =$A6*$B$18*(B$4-$B$16)-$B$17 -> 0 | C6: =$A6*$B$18*(C$4-$B$16)-$B$17 -> 20 | D6: =$A6*$B$18*(D$4-$B$16)-$B$17 -> 40 | E6: =$A6*$B$18*(E$4-$B$16)-$B$17 -> 60 | F6: =$A6*$B$18*(F$4-$B$16)-$B$17 -> 80
A7: 30 | B7: =$A7*$B$18*(B$4-$B$16)-$B$17 -> 80 | C7: =$A7*$B$18*(C$4-$B$16)-$B$17 -> 110 | D7: =$A7*$B$18*(D$4-$B$16)-$B$17 -> 140 | E7: =$A7*$B$18*(E$4-$B$16)-$B$17 -> 170 | F7: =$A7*$B$18*(F$4-$B$16)-$B$17 -> 200
A8: 40 | B8: =$A8*$B$18*(B$4-$B$16)-$B$17 -> 160 | C8: =$A8*$B$18*(C$4-$B$16)-$B$17 -> 200 | D8: =$A8*$B$18*(D$4-$B$16)-$B$17 -> 240 | E8: =$A8*$B$18*(E$4-$B$16)-$B$17 -> 280 | F8: =$A8*$B$18*(F$4-$B$16)-$B$17 -> 320
A9: 50 | B9: =$A9*$B$18*(B$4-$B$16)-$B$17 -> 240 | C9: =$A9*$B$18*(C$4-$B$16)-$B$17 -> 290 | D9: =$A9*$B$18*(D$4-$B$16)-$B$17 -> 340 | E9: =$A9*$B$18*(E$4-$B$16)-$B$17 -> 390 | F9: =$A9*$B$18*(F$4-$B$16)-$B$17 -> 440
A10: 60 | B10: =$A10*$B$18*(B$4-$B$16)-$B$17 -> 320 | C10: =$A10*$B$18*(C$4-$B$16)-$B$17 -> 380 | D10: =$A10*$B$18*(D$4-$B$16)-$B$17 -> 440 | E10: =$A10*$B$18*(E$4-$B$16)-$B$17 -> 500 | F10: =$A10*$B$18*(F$4-$B$16)-$B$17 -> 560
A11: 70 | B11: =$A11*$B$18*(B$4-$B$16)-$B$17 -> 400 | C11: =$A11*$B$18*(C$4-$B$16)-$B$17 -> 470 | D11: =$A11*$B$18*(D$4-$B$16)-$B$17 -> 540 | E11: =$A11*$B$18*(E$4-$B$16)-$B$17 -> 610 | F11: =$A11*$B$18*(F$4-$B$16)-$B$17 -> 680
A12: 80 | B12: =$A12*$B$18*(B$4-$B$16)-$B$17 -> 480 | C12: =$A12*$B$18*(C$4-$B$16)-$B$17 -> 560 | D12: =$A12*$B$18*(D$4-$B$16)-$B$17 -> 640 | E12: =$A12*$B$18*(E$4-$B$16)-$B$17 -> 720 | F12: =$A12*$B$18*(F$4-$B$16)-$B$17 -> 800
A13: 90 | B13: =$A13*$B$18*(B$4-$B$16)-$B$17 -> 560 | C13: =$A13*$B$18*(C$4-$B$16)-$B$17 -> 650 | D13: =$A13*$B$18*(D$4-$B$16)-$B$17 -> 740 | E13: =$A13*$B$18*(E$4-$B$16)-$B$17 -> 830 | F13: =$A13*$B$18*(F$4-$B$16)-$B$17 -> 920
A14: 100 | B14: =$A14*$B$18*(B$4-$B$16)-$B$17 -> 640 | C14: =$A14*$B$18*(C$4-$B$16)-$B$17 -> 740 | D14: =$A14*$B$18*(D$4-$B$16)-$B$17 -> 840 | E14: =$A14*$B$18*(E$4-$B$16)-$B$17 -> 940 | F14: =$A14*$B$18*(F$4-$B$16)-$B$17 -> 1040
A16: Ingredient cost per item | B16: =IF(Projection!C19=0,0,Projection!C15/Projection!C19) -> 0 | C16: From the expected mix on Projection.
A17: Fixed costs | B17: =Inputs!B17 -> 160
A18: Days open | B18: =Inputs!B20 -> 2
A20: Your menu averages about $5 per item. Read down the $5.00 column to see how many items a day you need.

Sheet Stock plan
A1: Stock Plan
A2: Checks whether what you're making covers the projected weekend sales. Enter stock on the Inputs tab.
A4: Item | B4: Stock prepared | C4: Expected units | D4: High units | E4: Left over (expected) | F4: Sales if all stock sells ($) | G4: Status
A5: =IF(Inputs!A5="","",Inputs!A5) -> Medhu Vadai | B5: =Inputs!E5 -> 50 | C5: =Projection!E5 -> 40 | D5: =Projection!G5 -> 70 | E5: =IF(OR(A5="",Inputs!E5=""),0,B5-C5) -> 10 | F5: =B5*Inputs!C5 -> 300 | G5: =IF(A5="","",IF(Inputs!E5="","Enter stock on Inputs",IF(B5>=D5,"Enough even for a busy weekend",IF(B5>=C5,"Enough for expected","Short by "&(C5-B5)&" for expected")))) -> Enough for expected
A6: =IF(Inputs!A6="","",Inputs!A6) -> Paneer Puff | B6: =Inputs!E6 -> 40 | C6: =Projection!E6 -> 40 | D6: =Projection!G6 -> 70 | E6: =IF(OR(A6="",Inputs!E6=""),0,B6-C6) -> 0 | F6: =B6*Inputs!C6 -> 160 | G6: =IF(A6="","",IF(Inputs!E6="","Enter stock on Inputs",IF(B6>=D6,"Enough even for a busy weekend",IF(B6>=C6,"Enough for expected","Short by "&(C6-B6)&" for expected")))) -> Enough for expected
A7: =IF(Inputs!A7="","",Inputs!A7) -> Podi Idly | B7: =Inputs!E7 -> 30 | C7: =Projection!E7 -> 30 | D7: =Projection!G7 -> 50 | E7: =IF(OR(A7="",Inputs!E7=""),0,B7-C7) -> 0 | F7: =B7*Inputs!C7 -> 240 | G7: =IF(A7="","",IF(Inputs!E7="","Enter stock on Inputs",IF(B7>=D7,"Enough even for a busy weekend",IF(B7>=C7,"Enough for expected","Short by "&(C7-B7)&" for expected")))) -> Enough for expected
A8: =IF(Inputs!A8="","",Inputs!A8) -> Rose Milk | B8: =Inputs!E8 -> 20 | C8: =Projection!E8 -> 50 | D8: =Projection!G8 -> 80 | E8: =IF(OR(A8="",Inputs!E8=""),0,B8-C8) -> -30 | F8: =B8*Inputs!C8 -> 80 | G8: =IF(A8="","",IF(Inputs!E8="","Enter stock on Inputs",IF(B8>=D8,"Enough even for a busy weekend",IF(B8>=C8,"Enough for expected","Short by "&(C8-B8)&" for expected")))) -> Short by 30 for expected
A9: =IF(Inputs!A9="","",Inputs!A9) | B9: =Inputs!E9 -> 0 | C9: =Projection!E9 -> 0 | D9: =Projection!G9 -> 0 | E9: =IF(OR(A9="",Inputs!E9=""),0,B9-C9) -> 0 | F9: =B9*Inputs!C9 -> 0 | G9: =IF(A9="","",IF(Inputs!E9="","Enter stock on Inputs",IF(B9>=D9,"Enough even for a busy weekend",IF(B9>=C9,"Enough for expected","Short by "&(C9-B9)&" for expected"))))
A10: =IF(Inputs!A10="","",Inputs!A10) | B10: =Inputs!E10 -> 0 | C10: =Projection!E10 -> 0 | D10: =Projection!G10 -> 0 | E10: =IF(OR(A10="",Inputs!E10=""),0,B10-C10) -> 0 | F10: =B10*Inputs!C10 -> 0 | G10: =IF(A10="","",IF(Inputs!E10="","Enter stock on Inputs",IF(B10>=D10,"Enough even for a busy weekend",IF(B10>=C10,"Enough for expected","Short by "&(C10-B10)&" for expected"))))
A11: Total | B11: =SUM(B5:B10) -> 140 | C11: =SUM(C5:C10) -> 160 | D11: =SUM(D5:D10) -> 270 | E11: =SUM(E5:E10) -> -20 | F11: =SUM(F5:F10) -> 780
A13: Left over below zero means you'd sell out before the expected number. Sales if all stock sells is the most you can earn with that stock.

Sheet Actuals
A1: Actuals vs Projection
A2: After the weekend, enter units sold from the tracker's Summary export (the Sold column). Actual sales = price x units sold. Yellow cells are yours to fill.
A4: Item | B4: Price ($) | C4: Expected units | D4: Actual units sold | E4: Difference (units) | F4: Expected sales ($) | G4: Actual sales ($) = price x units
A5: =IF(Inputs!A5="","",Inputs!A5) -> Medhu Vadai | B5: =Inputs!C5 -> 6 | C5: =Projection!E5 -> 40 | E5: =IF(D5="",0,D5-C5) -> 0 | F5: =B5*C5 -> 240 | G5: =B5*D5 -> 0
A6: =IF(Inputs!A6="","",Inputs!A6) -> Paneer Puff | B6: =Inputs!C6 -> 4 | C6: =Projection!E6 -> 40 | E6: =IF(D6="",0,D6-C6) -> 0 | F6: =B6*C6 -> 160 | G6: =B6*D6 -> 0
A7: =IF(Inputs!A7="","",Inputs!A7) -> Podi Idly | B7: =Inputs!C7 -> 8 | C7: =Projection!E7 -> 30 | E7: =IF(D7="",0,D7-C7) -> 0 | F7: =B7*C7 -> 240 | G7: =B7*D7 -> 0
A8: =IF(Inputs!A8="","",Inputs!A8) -> Rose Milk | B8: =Inputs!C8 -> 4 | C8: =Projection!E8 -> 50 | E8: =IF(D8="",0,D8-C8) -> 0 | F8: =B8*C8 -> 200 | G8: =B8*D8 -> 0
A9: =IF(Inputs!A9="","",Inputs!A9) | B9: =Inputs!C9 -> 0 | C9: =Projection!E9 -> 0 | E9: =IF(D9="",0,D9-C9) -> 0 | F9: =B9*C9 -> 0 | G9: =B9*D9 -> 0
A10: =IF(Inputs!A10="","",Inputs!A10) | B10: =Inputs!C10 -> 0 | C10: =Projection!E10 -> 0 | E10: =IF(D10="",0,D10-C10) -> 0 | F10: =B10*C10 -> 0 | G10: =B10*D10 -> 0
A11: Total | C11: =SUM(C5:C10) -> 160 | D11: =SUM(D5:D10) -> 0 | E11: =SUM(E5:E10) -> 0 | F11: =SUM(F5:F10) -> 840 | G11: =SUM(G5:G10) -> 0
A13: Profit | B13: Expected | C13: Actual
A14: Sales | B14: =F11 -> 840 | C14: =G11 -> 0
A15: Ingredient cost (per-unit) | B15: =Projection!C15 -> 0 | C15: =SUMPRODUCT(D5:D10,Inputs!$D$5:$D$10) -> 0
A16: Spend | B16: =Inputs!B17 -> 160 | C16: =Inputs!B17 -> 160 | D16: Type over this with your real total spend from the tracker if it changed.
A17: Profit / loss | B17: =B14-B15-B16 -> 680 | C17: =C14-C15-C16 -> -160
A18: Actual vs expected | C18: =C17-B17 -> -840
A20: Leave Actual units blank until the weekend is done. Until then, Actual shows a loss of your spend.
